out/__init__.py
out/demos.py
out/detection.py
out/format.py
out/highlight.py
out/test_mod.py
out/themes.py
out-0.80.dist-info/LICENSE
out-0.80.dist-info/METADATA
out-0.80.dist-info/WHEEL
out-0.80.dist-info/top_level.txt
out-0.80.dist-info/RECORD
